[{"id":"42e1f150aa0ac41ecbb8c656c1df12b5","type":"movie","week":"m","img":"http://www.666zy.com/upload/vod/2019-01-15/15475411014.jpg","title":"喜剧之王2预告片","actor":"妻夫木聡,池胁千鹤,上野樹里,菅野莉央,新井浩文,江口德子,荒川良良,森下能幸,板尾创路,萨布","time":"2019-01-24","link":"http://www.123123mv.com/index.php/voddetail-7082.html","episodes":[{"text":"바로재생","src":"//123123mv.com/dp/mp4.php?url=https://cdn-3.haku99.com/hls/2019/01/15/UmaDA3XJ/playlist.m3u8"}],"country":"香港","year":""},{"id":"e2de0ee1a57a0ecada1ceaa2fd803015","type":"movie","week":"m","img":"http://www.666zy.com/upload/vod/2019-01-12/15472687365.jpg","title":"铜雀台","actor":"周润发,刘亦菲,苏有朋,玉木宏,伊能静,邱心志,姚橹,倪大红,牛犇,罗家英,保剑锋,池程,王洪千,曲泉丞,彭敬慈,张籽沐,刘杰毅,郭金非,田瑞辉,颜冠英,金延虎,李胜达,王羽铮,王祖卿,付俊龙","time":"2019-01-24","link":"http://www.123123mv.com/index.php/voddetail-6241.html","episodes":[{"text":"HD","src":"//123123mv.com/dp/mp4.php?url=https://cdn-3.haku99.com/hls/2019/01/10/pS8oDXTq/playlist.m3u8"}],"country":"大陆","year":""},{"id":"e3739e0b07f0137f1a78cf94bcd9979d","type":"movie","week":"m","img":"http://www.666zy.com/upload/vod/2019-01-16/201901161547570791.jpg","title":"古院迷情","actor":"楚建,,金东黎","time":"2019-01-24","link":"http://www.123123mv.com/index.php/voddetail-7077.html","episodes":[{"text":"BD国语","src":"//123123mv.com/dp/mp4.php?url=https://cdn-3.haku99.com/hls/2019/01/15/xVhjZTzl/playlist.m3u8"}],"country":"大陆","year":""},{"id":"8660fa005dac81656ed9bb3bb265bd4e","type":"movie","week":"m","img":"http://www.666zy.com/upload/vod/2019-01-15/154755683914.jpg","title":"变节：潜罪犯","actor":"谢天华,吴镇宇,黄宗泽,杜汶泽,惠英红,徐子珊,文咏珊,廖启智,麦长青,林雪,金刚,欧阳靖,蒋志光,刘兆铭,朱晨丽","time":"2019-01-24","link":"http://www.123123mv.com/index.php/voddetail-7056.html","episodes":[{"text":"BD中字","src":"//123123mv.com/dp/mp4.php?url=https://cdn-3.haku99.com/hls/2019/01/15/fhjR0ASJ/playlist.m3u8"}],"country":"香港","year":""},{"id":"c0f402fdba5175fe2a9da05dfb1d92d4","type":"movie","week":"m","img":"http://www.666zy.com/upload/vod/2019-01-16/15475897482.jpg","title":"后院有宝","actor":"修宗迪,雷恪生","time":"2019-01-24","link":"http://www.123123mv.com/index.php/voddetail-7079.html","episodes":[{"text":"HD国语中字","src":"//123123mv.com/dp/mp4.php?url=https://cdn-3.haku99.com/hls/2019/01/15/8gdJVRNU/playlist.m3u8"}],"country":"大陆","year":""},{"id":"6aaadfbf8202f95faf982304a4365f00","type":"movie","week":"m","img":"http://www.666zy.com/upload/vod/2019-01-15/154756512015.jpg","title":"丢羊","actor":"任帅","time":"2019-01-24","link":"http://www.123123mv.com/index.php/voddetail-7058.html","episodes":[{"text":"HD","src":"//123123mv.com/dp/mp4.php?url=https://cdn-3.haku99.com/hls/2019/01/15/pcxZPqOK/playlist.m3u8"}],"country":"大陆","year":""},{"id":"b1b1b375afe72e57d0c44e5971ac1d99","type":"movie","week":"m","img":"http://www.666zy.com/upload/vod/2019-01-16/15475897481.jpg","title":"寻找同桌的你","actor":"汤加丽,马诺,易欣,储毅","time":"2019-01-24","link":"http://www.123123mv.com/index.php/voddetail-7075.html","episodes":[{"text":"HD1280超清国语中字","src":"//123123mv.com/dp/mp4.php?url=https://cdn-3.haku99.com/hls/2019/01/15/z7MSmhqE/playlist.m3u8"}],"country":"大陆","year":""},{"id":"2628e8e11ddf6b418d4870f7dd8f4823","type":"movie","week":"m","img":"http://www.666zy.com/upload/vod/2019-01-15/15475651189.jpg","title":"魔幻神功","actor":"高文松,蒋琳琳,谢昀融,多多,辉扬,马场,陈婉芝,赵美姿","time":"2019-01-24","link":"http://www.123123mv.com/index.php/voddetail-7049.html","episodes":[{"text":"바로재생","src":"//123123mv.com/dp/mp4.php?url=https://cdn-3.haku99.com/hls/2019/01/15/Vp2diL3X/playlist.m3u8"}],"country":"香港","year":""},{"id":"849b673736ed52803e725f208a2febf0","type":"movie","week":"m","img":"http://www.666zy.com/upload/vod/2019-01-17/201901171547732095.jpg","title":"整心计","actor":"陈炳强,文东俊,徐巾淇","time":"2019-01-24","link":"http://www.123123mv.com/index.php/voddetail-7343.html","episodes":[{"text":"超清(720P","src":"//123123mv.com/dp/mp4.php?url=https://cdn-3.haku99.com/hls/2019/01/17/VYhYEd4J/playlist.m3u8"}],"country":"大陆","year":""},{"id":"6b534ec5391faf3d20f42c1ffcd11bfa","type":"movie","week":"m","img":"http://www.666zy.com/upload/vod/2019-01-12/154725613315.jpg","title":"九星报喜","actor":"张国荣,吴倩莲,钟镇涛,李蕙敏,张达明,黎姿,黄百鸣,陈洁灵,周文健,雷宇扬","time":"2019-01-24","link":"http://www.123123mv.com/index.php/voddetail-6209.html","episodes":[{"text":"바로재생","src":"//123123mv.com/dp/mp4.php?url=https://cdn-3.haku99.com/hls/2019/01/10/Sup5ihH8/playlist.m3u8"}],"country":"香港","year":""},{"id":"976a59c0bfc8a493d541384438a8c9b0","type":"movie","week":"m","img":"http://www.666zy.com/upload/vod/2019-01-15/15475651262.jpg","title":"鬼马双星","actor":"许冠文,许冠杰,许冠英,吕有慧,乔宏,罗兰,丁佩,许绍雄","time":"2019-01-24","link":"http://www.123123mv.com/index.php/voddetail-7045.html","episodes":[{"text":"바로재생","src":"//123123mv.com/dp/mp4.php?url=https://cdn-3.haku99.com/hls/2019/01/15/FIXYRYpz/playlist.m3u8"}],"country":"香港","year":""},{"id":"321b6f99c5013fdef3a04e592720882b","type":"movie","week":"m","img":"http://www.666zy.com/upload/vod/2019-01-15/154755682810.jpg","title":"靠岸","actor":"李勇,吴颖,康殿宏,郑明泰","time":"2019-01-24","link":"http://www.123123mv.com/index.php/voddetail-7030.html","episodes":[{"text":"BD国语中字","src":"//123123mv.com/dp/mp4.php?url=https://cdn-3.haku99.com/hls/2019/01/15/VeuYhce7/playlist.m3u8"}],"country":"台湾","year":""},{"id":"64b3c7818d1bee0bf59ae43caed1a32e","type":"movie","week":"m","img":"http://www.666zy.com/upload/vod/2019-01-15/15475651240.jpg","title":"无品大将迷魂战","actor":"方安娜,洪尧","time":"2019-01-24","link":"http://www.123123mv.com/index.php/voddetail-7046.html","episodes":[{"text":"바로재생","src":"//123123mv.com/dp/mp4.php?url=https://cdn-3.haku99.com/hls/2019/01/15/w7Co058P/playlist.m3u8"}],"country":"大陆","year":""},{"id":"7f5c9bbf7e685fdd94b23d3d5e044ffe","type":"movie","week":"m","img":"http://www.666zy.com/upload/vod/2019-01-15/15475568351.jpg","title":"新方世玉","actor":"陈永霞,史宝华","time":"2019-01-24","link":"http://www.123123mv.com/index.php/voddetail-7031.html","episodes":[{"text":"바로재생","src":"//123123mv.com/dp/mp4.php?url=https://cdn-3.haku99.com/hls/2019/01/15/H4zrZNCt/playlist.m3u8"}],"country":"大陆","year":""},{"id":"50c8c64701eef4343982b72db345f20c","type":"movie","week":"m","img":"http://www.666zy.com/upload/vod/2019-01-15/154755683810.jpg","title":"梁山伯与祝英台","actor":"凌波,乐蒂,任洁,井淼,高宝树","time":"2019-01-24","link":"http://www.123123mv.com/index.php/voddetail-7047.html","episodes":[{"text":"BD国语中字","src":"//123123mv.com/dp/mp4.php?url=https://cdn-3.haku99.com/hls/2019/01/15/ew1lOQ1C/playlist.m3u8"}],"country":"香港","year":""},{"id":"441ad5293d6302ee4c254d5bd24891c5","type":"movie","week":"m","img":"http://www.666zy.com/upload/vod/2019-01-15/15475568288.jpg","title":"枪王","actor":"张国荣,方中信,黄卓玲,陈法蓉,谷德昭,陈望华","time":"2019-01-24","link":"http://www.123123mv.com/index.php/voddetail-7026.html","episodes":[{"text":"BD中字","src":"//123123mv.com/dp/mp4.php?url=https://cdn-3.haku99.com/hls/2019/01/15/Tye51FZt/playlist.m3u8"}],"country":"香港","year":""},{"id":"9c36bbbafce782cc64421d541e57c0ad","type":"movie","week":"m","img":"http://www.666zy.com/upload/vod/2019-01-11/15471784143.jpg","title":"爱的发声练习","actor":"徐熙媛,彭于晏,张孝全,东明相,李国毅","time":"2019-01-24","link":"http://www.123123mv.com/index.php/voddetail-7039.html","episodes":[{"text":"第01集","src":"//123123mv.com/dp/mp4.php?url=https://cdn-3.haku99.com/hls/2019/01/09/D0gxuogw/playlist.m3u8"},{"text":"第02集","src":"//123123mv.com/dp/mp4.php?url=https://cdn-3.haku99.com/hls/2019/01/09/Kn2Xn56c/playlist.m3u8"},{"text":"바로재생","src":"//123123mv.com/dp/mp4.php?url=https://cdn-3.haku99.com/hls/2019/01/15/XNTM2UpZ/playlist.m3u8"}],"country":"台湾","year":""},{"id":"901b9bb77bf2c0b67aa510672f5c2d85","type":"movie","week":"m","img":"http://www.666zy.com/upload/vod/2019-01-15/15475411015.jpg","title":"百年好合","actor":"郑秀文,古天乐,李冰冰,林雪,韩君婷,张锦程,夏雨,颜颖思","time":"2019-01-24","link":"http://www.123123mv.com/index.php/voddetail-7013.html","episodes":[{"text":"바로재생","src":"//123123mv.com/dp/mp4.php?url=https://cdn-3.haku99.com/hls/2019/01/15/4V9cG9SN/playlist.m3u8"}],"country":"香港","year":""},{"id":"f21391d199a49159b4b1af0f6113dd9f","type":"movie","week":"m","img":"http://www.666zy.com/upload/vod/2019-01-17/201901171547732182.jpg","title":"主播流浪记","actor":"任山,吴晓敏","time":"2019-01-24","link":"http://www.123123mv.com/index.php/voddetail-7346.html","episodes":[{"text":"超清(720P)","src":"//123123mv.com/dp/mp4.php?url=https://cdn-3.haku99.com/hls/2019/01/17/JNBgtDio/playlist.m3u8"}],"country":"大陆","year":""},{"id":"0559ee7302133713f6374c7f5de81c3e","type":"movie","week":"m","img":"http://www.666zy.com/upload/vod/2019-01-12/154726874710.jpg","title":"王牌情敌/我爱HK恭囍发财","actor":"谭咏麟,陈百祥,叶玉卿,曾志伟,冯淬帆,黄宗泽,谢天华,徐子珊,郑欣宜","time":"2019-01-24","link":"http://www.123123mv.com/index.php/voddetail-7004.html","episodes":[{"text":"바로재생","src":"//123123mv.com/dp/mp4.php?url=https://cdn-3.haku99.com/hls/2019/01/10/h7jI20t8/playlist.m3u8"}],"country":"香港","year":""}]