[{"id":"8e94c256eacc29f7b48ea517628dc1f6","type":"movie","week":"m","img":"http://www.666zy.com/upload/vod/2019-01-19/15478302190.jpg","title":"铁血娇娃","actor":"邹兆龙,余男,释行宇,安志杰,潘霜霜,王丹怡栗,史梵希,木幡龙,胡梦媛,吴静一,王秋紫,谈莉娜","time":"2019-01-24","link":"http://www.123123mv.com/index.php/voddetail-7445.html","episodes":[{"text":"HD国语中字","src":"//123123mv.com/dp/mp4.php?url=https://cdn-3.haku99.com/hls/2019/01/18/SumKE8xg/playlist.m3u8"}],"country":"大陆","year":""},{"id":"fbe8d1ef46d3c5c2b2d9161db1c39849","type":"movie","week":"m","img":"http://www.666zy.com/upload/vod/2019-01-16/154765125319.jpg","title":"一条没有变成蓝色的鱼","actor":"张钧甯,韦瑮,周云深","time":"2019-01-24","link":"http://www.123123mv.com/index.php/voddetail-7223.html","episodes":[{"text":"超清(720P)","src":"//123123mv.com/dp/mp4.php?url=https://cdn-2.haku99.com/hls/2019/01/16/FYvPuAvV/playlist.m3u8"}],"country":"大陆","year":""},{"id":"9973d1491632d70a2c4ca64e3d90d8ff","type":"movie","week":"m","img":"http://www.666zy.com/upload/vod/2019-01-19/15478302193.jpg","title":"少林童子功","actor":"王丽莎,张龙,王庆玉","time":"2019-01-24","link":"http://www.123123mv.com/index.php/voddetail-7450.html","episodes":[{"text":"바로재생","src":"//123123mv.com/dp/mp4.php?url=https://cdn-3.haku99.com/hls/2019/01/18/3XLiN0f7/playlist.m3u8"}],"country":"大陆","year":""},{"id":"d2b1a310d0a4b35c0231625d0839599a","type":"movie","week":"m","img":"http://www.666zy.com/upload/vod/2019-01-16/201901161547649090.jpg","title":"电竞之王","actor":"林申,米娜,李晓峰","time":"2019-01-24","link":"http://www.123123mv.com/index.php/voddetail-7224.html","episodes":[{"text":"超清(720P)","src":"//123123mv.com/dp/mp4.php?url=https://cdn-3.haku99.com/hls/2019/01/16/bEs1tdeW/playlist.m3u8"}],"country":"大陆","year":""},{"id":"d7fb5ffdcc4dc1ef5860a0e7af8a05b0","type":"movie","week":"m","img":"http://www.666zy.com/upload/vod/2019-01-19/15479003254.jpg","title":"不可抗力爱上你","actor":"孟瑞,王博文","time":"2019-01-24","link":"http://www.123123mv.com/index.php/voddetail-7449.html","episodes":[{"text":"바로재생","src":"//123123mv.com/dp/mp4.php?url=https://cdn-3.haku99.com/hls/2019/01/19/b2rQYqrk/playlist.m3u8"}],"country":"大陆","year":""},{"id":"68a4202e014c4b3d340f29441d8a3f1c","type":"movie","week":"m","img":"http://www.666zy.com/upload/vod/2019-01-16/201901161547640414.jpg","title":"农村合伙人","actor":"武裔风,付宇龙,李凌瑞","time":"2019-01-24","link":"http://www.123123mv.com/index.php/voddetail-7216.html","episodes":[{"text":"超清(720P)","src":"//123123mv.com/dp/mp4.php?url=https://cdn-3.haku99.com/hls/2019/01/16/NrJ779ed/playlist.m3u8"}],"country":"大陆","year":""},{"id":"9be89c937753487800c55a6ba0386029","type":"movie","week":"m","img":"http://www.666zy.com/upload/vod/2019-01-19/15478302215.jpg","title":"祝您好运","actor":"万梓良,梅艳芳,袁祥仁","time":"2019-01-24","link":"http://www.123123mv.com/index.php/voddetail-7456.html","episodes":[{"text":"바로재생","src":"//123123mv.com/dp/mp4.php?url=https://cdn-3.haku99.com/hls/2019/01/18/0VdrcRyi/playlist.m3u8"}],"country":"香港","year":""},{"id":"f0fd05c95ffa42496e304be6e8cf95b9","type":"movie","week":"m","img":"http://www.666zy.com/upload/vod/2019-01-16/15476400178.jpg","title":"圈子之德州风云","actor":"张哲浩","time":"2019-01-24","link":"http://www.123123mv.com/index.php/voddetail-7217.html","episodes":[{"text":"超清(720P)","src":"//123123mv.com/dp/mp4.php?url=https://cdn-3.haku99.com/hls/2019/01/16/h70s5biA/playlist.m3u8"}],"country":"大陆","year":""},{"id":"7f3270ebfd840500d3e26d82effd0bda","type":"movie","week":"m","img":"http://www.666zy.com/upload/vod/2019-01-19/154783022313.jpg","title":"啥是佩奇","actor":"","time":"2019-01-24","link":"http://www.123123mv.com/index.php/voddetail-7465.html","episodes":[{"text":"点击播放","src":"//123123mv.com/dp/mp4.php?url=https://youku163.zuida-bofang.com/20190119/25279_5ec42696/index.m3u8"}],"country":"大陆","year":""},{"id":"3bbee07ffb997d25b2d186f8bc552f93","type":"movie","week":"m","img":"http://www.666zy.com/upload/vod/2019-01-16/154765125318.jpg","title":"七个隆咚锵咚锵","actor":"韩兆,杨少华,刘亚津,张楚焱,郜妍","time":"2019-01-24","link":"http://www.123123mv.com/index.php/voddetail-7218.html","episodes":[{"text":"바로재생","src":"//123123mv.com/dp/mp4.php?url=https://cdn-3.haku99.com/hls/2019/01/16/0ccAdw3M/playlist.m3u8"}],"country":"大陆","year":""},{"id":"46f49458da64367da0daf9571403398d","type":"movie","week":"m","img":"http://www.666zy.com/upload/vod/2019-01-12/15472561403.jpg","title":"立春","actor":"冷美(杜丹)","time":"2019-01-24","link":"http://www.123123mv.com/index.php/voddetail-6218.html","episodes":[{"text":"바로재생","src":"//123123mv.com/dp/mp4.php?url=https://cdn-3.haku99.com/hls/2019/01/10/MrmT52hb/playlist.m3u8"}],"country":"大陆","year":""},{"id":"7e4a1c8e04267a224ccfb127a93a0b46","type":"movie","week":"m","img":"http://www.666zy.com/upload/vod/2019-01-16/15476512515.jpg","title":"魔兽之副本人生","actor":"李俊睿,袁媛","time":"2019-01-24","link":"http://www.123123mv.com/index.php/voddetail-7210.html","episodes":[{"text":"超清(720P)","src":"//123123mv.com/dp/mp4.php?url=https://cdn-3.haku99.com/hls/2019/01/16/gsMAS6MV/playlist.m3u8"}],"country":"大陆","year":""},{"id":"fcd30bf77fb12b64334ae4547355df1d","type":"movie","week":"m","img":"http://www.666zy.com/upload/vod/2019-01-19/15479003717.jpg","title":"雪山惊魂2","actor":"Ingrid,Marthe,Kim,Mats","time":"2019-01-24","link":"http://www.123123mv.com/index.php/voddetail-7484.html","episodes":[{"text":"바로재생","src":"//123123mv.com/dp/mp4.php?url=https://cdn-3.haku99.com/hls/2019/01/19/UQiwKYsC/playlist.m3u8"}],"country":"大陆","year":""},{"id":"99c7069583aa4f255f98dfe70b323568","type":"movie","week":"m","img":"http://www.666zy.com/upload/vod/2019-01-16/201901161547639842.jpg","title":"人质","actor":"林晓凡,张维伊","time":"2019-01-24","link":"http://www.123123mv.com/index.php/voddetail-7211.html","episodes":[{"text":"超清(720P)","src":"//123123mv.com/dp/mp4.php?url=https://cdn-3.haku99.com/hls/2019/01/16/MD7bDzcB/playlist.m3u8"}],"country":"大陆","year":""},{"id":"1846175c8c80b8e0068035975b5696e9","type":"movie","week":"m","img":"http://www.666zy.com/upload/vod/2019-01-19/15479003791.jpg","title":"我的青春蜜友","actor":"孙茜,李泰,彭博,汤晶媚,张群,李若嘉,吴弘","time":"2019-01-24","link":"http://www.123123mv.com/index.php/voddetail-7483.html","episodes":[{"text":"HD.720p.国语中字","src":"//123123mv.com/dp/mp4.php?url=https://cdn-3.haku99.com/hls/2019/01/19/dKpDIaxK/playlist.m3u8"}],"country":"大陆","year":""},{"id":"c4b1b717b4a02cd56fc333fce5860739","type":"movie","week":"m","img":"http://www.666zy.com/upload/vod/2019-01-16/15476512516.jpg","title":"魔术大逃杀","actor":"王龙,邱子洛,周小羽,鞠然","time":"2019-01-24","link":"http://www.123123mv.com/index.php/voddetail-7213.html","episodes":[{"text":"蓝光(1080P)","src":"//123123mv.com/dp/mp4.php?url=https://cdn-3.haku99.com/hls/2019/01/16/cKzAi4vC/playlist.m3u8"}],"country":"大陆","year":""},{"id":"3c6136a59e5f06455d56af8478dea415","type":"movie","week":"m","img":"http://www.666zy.com/upload/vod/2019-01-19/15479003718.jpg","title":"半妖皇帝番外","actor":"陈圆","time":"2019-01-24","link":"http://www.123123mv.com/index.php/voddetail-7486.html","episodes":[{"text":"바로재생","src":"//123123mv.com/dp/mp4.php?url=https://cdn-3.haku99.com/hls/2019/01/19/xvwJ1lcT/playlist.m3u8"}],"country":"大陆","year":""},{"id":"f33ae6238c3c5d2363582560925e1522","type":"movie","week":"m","img":"http://www.666zy.com/upload/vod/2019-01-16/15476400179.jpg","title":"奇葩双人行之战杭州","actor":"张艺骞,杨蕊丞,陈家君,郭强","time":"2019-01-24","link":"http://www.123123mv.com/index.php/voddetail-7214.html","episodes":[{"text":"蓝光(1080P)","src":"//123123mv.com/dp/mp4.php?url=https://cdn-3.haku99.com/hls/2019/01/16/ngTvzkZm/playlist.m3u8"}],"country":"大陆","year":""},{"id":"8f606fb75d69734346dbb390147f83b5","type":"movie","week":"m","img":"http://www.666zy.com/upload/vod/2019-01-19/15479003794.jpg","title":"我的狗狗我的爱","actor":"黄翠如,黄淑仪,王凯","time":"2019-01-24","link":"http://www.123123mv.com/index.php/voddetail-7489.html","episodes":[{"text":"HD1024高清国语中字","src":"//123123mv.com/dp/mp4.php?url=https://cdn-3.haku99.com/hls/2019/01/19/9XtCr4Se/playlist.m3u8"}],"country":"香港","year":""},{"id":"413b30695eac33bb05e34907a51dda2f","type":"movie","week":"m","img":"http://www.666zy.com/upload/vod/2019-01-16/154765125215.jpg","title":"与敌同行（粤语）","actor":"郭晋安,郑嘉颖,蒙嘉慧","time":"2019-01-24","link":"http://www.123123mv.com/index.php/voddetail-7209.html","episodes":[{"text":"第01集","src":"//123123mv.com/dp/mp4.php?url=https://cdn-3.haku99.com/hls/2019/01/16/Y2xv1lFh/playlist.m3u8"},{"text":"第02集","src":"//123123mv.com/dp/mp4.php?url=https://cdn-3.haku99.com/hls/2019/01/16/VOblphxf/playlist.m3u8"},{"text":"第03集","src":"//123123mv.com/dp/mp4.php?url=https://cdn-3.haku99.com/hls/2019/01/16/mQH9Qyh4/playlist.m3u8"},{"text":"第04集","src":"//123123mv.com/dp/mp4.php?url=https://cdn-3.haku99.com/hls/2019/01/16/a1eSvfkA/playlist.m3u8"},{"text":"第05集","src":"//123123mv.com/dp/mp4.php?url=https://cdn-3.haku99.com/hls/2019/01/16/8fwZOoJH/playlist.m3u8"},{"text":"第06集","src":"//123123mv.com/dp/mp4.php?url=https://cdn-3.haku99.com/hls/2019/01/16/wR4xfJO8/playlist.m3u8"},{"text":"第07集","src":"//123123mv.com/dp/mp4.php?url=https://cdn-3.haku99.com/hls/2019/01/16/w26ZfTJV/playlist.m3u8"},{"text":"第08集","src":"//123123mv.com/dp/mp4.php?url=https://cdn-3.haku99.com/hls/2019/01/16/VwkXPBCS/playlist.m3u8"},{"text":"第09集","src":"//123123mv.com/dp/mp4.php?url=https://cdn-3.haku99.com/hls/2019/01/16/pYm2pnTX/playlist.m3u8"},{"text":"第10集","src":"//123123mv.com/dp/mp4.php?url=https://cdn-3.haku99.com/hls/2019/01/16/Ylpay1eS/playlist.m3u8"},{"text":"第11集","src":"//123123mv.com/dp/mp4.php?url=https://cdn-3.haku99.com/hls/2019/01/16/EWt4nfnW/playlist.m3u8"},{"text":"第12集","src":"//123123mv.com/dp/mp4.php?url=https://cdn-3.haku99.com/hls/2019/01/16/S66bDX2m/playlist.m3u8"},{"text":"第13集","src":"//123123mv.com/dp/mp4.php?url=https://cdn-3.haku99.com/hls/2019/01/16/N00e0XGl/playlist.m3u8"},{"text":"第14集","src":"//123123mv.com/dp/mp4.php?url=https://cdn-3.haku99.com/hls/2019/01/16/csAZL25O/playlist.m3u8"},{"text":"第15集","src":"//123123mv.com/dp/mp4.php?url=https://cdn-3.haku99.com/hls/2019/01/16/pUVEUfeM/playlist.m3u8"},{"text":"第16集","src":"//123123mv.com/dp/mp4.php?url=https://cdn-3.haku99.com/hls/2019/01/16/2GWk8Ggw/playlist.m3u8"},{"text":"第17集","src":"//123123mv.com/dp/mp4.php?url=https://cdn-3.haku99.com/hls/2019/01/16/lIFu2NZu/playlist.m3u8"},{"text":"第18集","src":"//123123mv.com/dp/mp4.php?url=https://cdn-3.haku99.com/hls/2019/01/16/7iNXPjnx/playlist.m3u8"},{"text":"第19集","src":"//123123mv.com/dp/mp4.php?url=https://cdn-3.haku99.com/hls/2019/01/16/ZPRDYvhJ/playlist.m3u8"},{"text":"第20集","src":"//123123mv.com/dp/mp4.php?url=https://cdn-3.haku99.com/hls/2019/01/16/JnvbZSkv/playlist.m3u8"},{"text":"第21集","src":"//123123mv.com/dp/mp4.php?url=https://cdn-3.haku99.com/hls/2019/01/16/jsC1hqtW/playlist.m3u8"},{"text":"第22集","src":"//123123mv.com/dp/mp4.php?url=https://cdn-3.haku99.com/hls/2019/01/16/GbBQzcMW/playlist.m3u8"}],"country":"香港","year":""}]