[{"id":"13c17f8d1f0c52a7ac69102d3be74d7d","type":"movie","week":"m","img":"https://tu.tianzuida.com/pic/upload/vod/2019-10-24/201910241571885439.jpg","title":"降龙觉醒","actor":"刘冠麟,朱丽岚,郑国霖,赵熠洋,金玄雨,郭振迦,卢夏禹,王陈怡娴","time":"2019-10-24","link":"http://www.123123mv.com/index.php/voddetail-18611.html","episodes":[{"text":"HD1280高清国语中字版","src":"https://hong.tianzhen-zuida.com/share/e1360bb1174a56e62f5a7d1194950342"}],"country":"大陆","year":""},{"id":"f7d94ae9b139b4275491e80d7cf9239e","type":"movie","week":"m","img":"https://tu.tianzuida.com/pic/upload/vod/2019-10-24/201910241571883631.jpg","title":"盛夏和她的未婚夫","actor":"肖雄,梁同裕,赵越,葛优","time":"2019-10-24","link":"http://www.123123mv.com/index.php/voddetail-18596.html","episodes":[{"text":"国语高清","src":"https://yi.jingdianzuida.com/share/Xbxmhspurn5taKzU"}],"country":"大陆","year":""},{"id":"2d2eb5377a7a8c50cd67a8f2fa648259","type":"movie","week":"m","img":"https://tu.tianzuida.com/pic/upload/vod/2019-10-24/201910241571884479.jpg","title":"父子婚事","actor":"葛优,丁一,葛存壮,徐峥","time":"2019-10-24","link":"http://www.123123mv.com/index.php/voddetail-18607.html","episodes":[{"text":"国语标清","src":"https://yi.jingdianzuida.com/share/8T9ylEc8t1MfQDSX"}],"country":"大陆","year":""},{"id":"6017e4b53d8bd10429ccfccbd709833a","type":"movie","week":"m","img":"https://tu.tianzuida.com/pic/upload/vod/2019-10-24/201910241571883802.jpg","title":"秦颂","actor":"姜文,葛优,许晴,戈治均,王庆祥,邸国强,李梦男","time":"2019-10-24","link":"http://www.123123mv.com/index.php/voddetail-18598.html","episodes":[{"text":"国语超清","src":"https://yi.jingdianzuida.com/share/xyU8xnpeyU9Vvtug"}],"country":"大陆","year":""},{"id":"65cd9effc031704760b2cf97d2811f7b","type":"movie","week":"m","img":"https://tu.tianzuida.com/pic/upload/vod/2019-10-24/201910241571884421.jpg","title":"过年","actor":"赵丽蓉,葛优,梁天,李保田,丁嘉丽,六小龄童,史兰芽,申军谊,胡亚捷,谭小燕,马晓晴,王丽云","time":"2019-10-24","link":"http://www.123123mv.com/index.php/voddetail-18606.html","episodes":[{"text":"国语超清","src":"https://yi.jingdianzuida.com/share/QTugLGxgU40B2BvJ"}],"country":"大陆","year":""},{"id":"a06b5897c5da3bce1967fd59dd73d36c","type":"movie","week":"m","img":"https://tu.tianzuida.com/pic/upload/vod/2019-10-24/201910241571883958.jpg","title":"女人TAXI女人","actor":"潘虹,丁嘉丽,葛优","time":"2019-10-24","link":"http://www.123123mv.com/index.php/voddetail-18600.html","episodes":[{"text":"国语高清","src":"https://yi.jingdianzuida.com/share/MdlZ3INiLD86DX9U"}],"country":"大陆","year":""},{"id":"5bccf227fd8729fcf6b62ec314f5987c","type":"movie","week":"m","img":"https://tu.tianzuida.com/pic/upload/vod/2019-10-24/201910241571884364.jpg","title":"黄河谣","actor":"巍子,葛优,曹景阳,迟蓬","time":"2019-10-24","link":"http://www.123123mv.com/index.php/voddetail-18605.html","episodes":[{"text":"国语标清","src":"https://yi.jingdianzuida.com/share/GHBH0ekkjyjmK1lh"}],"country":"大陆","year":""},{"id":"2c3a815248a30a71b4cdc7b73d8f96c3","type":"movie","week":"m","img":"https://tu.tianzuida.com/pic/upload/vod/2019-10-24/201910241571884025.jpg","title":"马路骑士","actor":"岳红,金莉莉,葛优,谢园","time":"2019-10-24","link":"http://www.123123mv.com/index.php/voddetail-18601.html","episodes":[{"text":"国语高清","src":"https://yi.jingdianzuida.com/share/TY8fUXUrsBItOKzT"}],"country":"大陆","year":""},{"id":"c4562a00bb569b1f8397a56933a0ac4b","type":"movie","week":"m","img":"https://tu.tianzuida.com/pic/upload/vod/2019-10-24/201910241571903453.jpg","title":"爸爸站起来","actor":"宋媛,吕永刚","time":"2019-10-24","link":"http://www.123123mv.com/index.php/voddetail-18619.html","episodes":[{"text":"HD1280高清国语中字版","src":"https://hong.tianzhen-zuida.com/share/3a90164865f389b757673ab3eafbcad9"}],"country":"大陆","year":""},{"id":"2ca47db151f9a95db0cc13668707caf2","type":"movie","week":"m","img":"https://tu.tianzuida.com/pic/upload/vod/2019-10-24/201910241571884078.jpg","title":"罗曼蒂克消亡史","actor":"葛优,章子怡,浅野忠信,杜淳,钟欣潼,倪大红,赵宝刚,袁泉,闫妮,韩庚,霍思燕,杜江,王传君,钟汉良,马晓伟,吕行,乔笑笑,刘天阳,赵海涛,叶禾,周敬峰,杨露璐,松峰莉璃,松浦敬之,平田康之,张晓龙,郭晓小,小黑","time":"2019-10-24","link":"http://www.123123mv.com/index.php/voddetail-18602.html","episodes":[{"text":"国语超清","src":"https://yi.jingdianzuida.com/share/TkdF6DOWjw0q0NzW"}],"country":"大陆","year":""},{"id":"b44824d9be8fb12b5809660c3149037d","type":"movie","week":"m","img":"http://www.666zy.com/upload/vod/2019-01-15/15475390270.jpg","title":"烈火金钢","actor":"申军谊,赵小锐,宋春丽,李强,葛优,梁天,舒耀宣,剧雪","time":"2019-10-24","link":"http://www.123123mv.com/index.php/voddetail-6949.html","episodes":[{"text":"国语超清","src":"https://yi.jingdianzuida.com/share/oqutJPL0JvXZ8bci"}],"country":"大陆","year":""},{"id":"9e664180c284408be9a69a4d744d72e5","type":"movie","week":"m","img":"https://tu.tianzuida.com/pic/upload/vod/2019-10-24/201910241571904005.jpg","title":"一路爱情","actor":"贾征宇,刘萌萌,张翔,姜语心,李肖宁,李萍,苗皓钧,马跃","time":"2019-10-24","link":"http://www.123123mv.com/index.php/voddetail-18617.html","episodes":[{"text":"HD1280高清国语中字版","src":"https://hong.tianzhen-zuida.com/share/0f06b381e883d28f330111747070706e"}],"country":"大陆","year":""},{"id":"558d6e71451266b408f3219cc3c36c41","type":"movie","week":"m","img":"https://tu.tianzuida.com/pic/upload/vod/2019-10-23/201910231571822590.jpg","title":"新赌国仇城","actor":"张铁林,林心如,吴奇隆,萧蔷,蓝正龙,王道,黄仲昆","time":"2019-10-23","link":"http://www.123123mv.com/index.php/voddetail-18579.html","episodes":[{"text":"国语高清","src":"https://yi.jingdianzuida.com/share/jRg4XApxpncSPFnW"}],"country":"香港","year":""},{"id":"b8a6543f74c34d0faec4476a362c171a","type":"movie","week":"m","img":"https://tu.tianzuida.com/pic/upload/vod/2019-10-23/201910231571797639.jpg","title":"镖行天下前传之四百里加急","actor":"吴奇隆,高亚麟,王鸥","time":"2019-10-23","link":"http://www.123123mv.com/index.php/voddetail-18560.html","episodes":[{"text":"HD国语中字","src":"https://yi.jingdianzuida.com/share/XzTLxQpUPuBBpBUU"}],"country":"大陆","year":""},{"id":"2e77e9729c27c371a86332ba611cc0a5","type":"movie","week":"m","img":"https://tu.tianzuida.com/pic/upload/vod/2019-10-23/201910231571797564.jpg","title":"镖行天下前传之至尊国宝","actor":"吴奇隆,徐亮,王鸥","time":"2019-10-23","link":"http://www.123123mv.com/index.php/voddetail-18561.html","episodes":[{"text":"HD国语中字","src":"https://yi.jingdianzuida.com/share/JznrXdJJrHr8BUrG"}],"country":"大陆","year":""},{"id":"7bafaa882d4ae888a6cc6570106f19d8","type":"movie","week":"m","img":"https://tu.tianzuida.com/pic/upload/vod/2019-10-23/201910231571797492.jpg","title":"镖行天下前传之库丁之谜","actor":"吴奇隆,刘波,王鸥","time":"2019-10-23","link":"http://www.123123mv.com/index.php/voddetail-18562.html","episodes":[{"text":"HD国语中字","src":"https://yi.jingdianzuida.com/share/oD17HtPeSHutdqL1"}],"country":"大陆","year":""},{"id":"82b2f6e156764cb79ed31aa49630ae2f","type":"movie","week":"m","img":"https://tu.tianzuida.com/pic/upload/vod/2019-10-23/201910231571797137.jpg","title":"镖行天下前传之燃眉危机","actor":"吴奇隆,王鸥,佟仲琪,徐亮","time":"2019-10-23","link":"http://www.123123mv.com/index.php/voddetail-18559.html","episodes":[{"text":"HD国语中字","src":"https://yi.jingdianzuida.com/share/II5uCVxulm0XxSfM"}],"country":"大陆","year":""},{"id":"1acdf8037cf68b42e982dd27300a4b80","type":"movie","week":"m","img":"https://tu.tianzuida.com/pic/upload/vod/2019-10-23/201910231571797796.jpg","title":"新喋血双雄","actor":"赵文瑄,刘若英,吴奇隆","time":"2019-10-23","link":"http://www.123123mv.com/index.php/voddetail-18565.html","episodes":[{"text":"国语标清","src":"https://yi.jingdianzuida.com/share/kmLZ6I41MRxvnCAu"}],"country":"香港","year":""},{"id":"4fbab3654d90c1e08482188e1eb8ca38","type":"movie","week":"m","img":"https://tu.tianzuida.com/pic/upload/vod/2019-10-23/201910231571818053.jpg","title":"契约少女管家","actor":"陆钧彦,王倩","time":"2019-10-23","link":"http://www.123123mv.com/index.php/voddetail-18578.html","episodes":[{"text":"HD1280高清国语中字版","src":"https://meng.wuyou-zuida.com/share/6afcddda4dd2ef353f099d5b78c5b517"}],"country":"大陆","year":""},{"id":"6cba01b04517f53f96a4ebe79983f74c","type":"movie","week":"m","img":"https://tu.tianzuida.com/pic/upload/vod/2019-10-23/201910231571795382.jpg","title":"有人说爱我","actor":"吴奇隆,朱茵,杜汶泽,廖启智,齐沚瑤,罗冠兰","time":"2019-10-23","link":"http://www.123123mv.com/index.php/voddetail-18545.html","episodes":[{"text":"粤语高清","src":"https://yi.jingdianzuida.com/share/zVXNYZZ8nbH3frBb"},{"text":"国语高清","src":"https://yi.jingdianzuida.com/share/M3JiU86mnZn4OusT"}],"country":"香港","year":""}]