[{"id":"f19b5a09fc038f1284dc3806a9909e99","type":"movie","week":"m","img":"http://www.666zy.com/upload/vod/2019-01-19/15479003701.jpg","title":"惊天绑架团","actor":"安东尼·霍普金斯,萨姆·沃辛顿,吉姆·斯特吉斯,瑞恩·柯万腾,杰迈玛·韦斯特,约兰特·卡鲍乌,艾力克·高敦,大卫·丹席克,比利·斯洛特,马克·范·伊文,托马斯·康奎尔","time":"2019-01-24","link":"http://www.123123mv.com/index.php/voddetail-7476.html","episodes":[{"text":"바로재생","src":"//123123mv.com/dp/mp4.php?url=https://cdn-3.haku99.com/hls/2019/01/19/9Je38saS/playlist.m3u8"}],"country":"英国","year":""},{"id":"48ec6421727fc3836cf4a9acb71626d7","type":"movie","week":"m","img":"http://www.666zy.com/upload/vod/2019-01-16/154761348610.jpg","title":"边境执行","actor":"莎朗·斯通,比利·赞恩,Rosemberg,Miguel","time":"2019-01-24","link":"http://www.123123mv.com/index.php/voddetail-7119.html","episodes":[{"text":"바로재생","src":"//123123mv.com/dp/mp4.php?url=https://cdn-3.haku99.com/hls/2019/01/16/bpnXoha7/playlist.m3u8"}],"country":"美国","year":""},{"id":"8bb5448d5ed74f3152b678b9fb88c419","type":"movie","week":"m","img":"http://www.666zy.com/upload/vod/2019-01-19/154790036017.jpg","title":"圣公会主学堂","actor":"阿什利·詹森,马丁·弗瑞曼,杰森·沃特金斯,马克·伍顿,杰弗里·哈钦斯,帕姆·费里斯,瑞奇·汤林森,菲利斯·洛根,约翰·塞森斯","time":"2019-01-24","link":"http://www.123123mv.com/index.php/voddetail-7474.html","episodes":[{"text":"바로재생","src":"//123123mv.com/dp/mp4.php?url=https://cdn-3.haku99.com/hls/2019/01/19/BA4b8tJK/playlist.m3u8"}],"country":"英国","year":""},{"id":"0178b11d7dca236b83abe9bc7cc1df9d","type":"movie","week":"m","img":"http://www.666zy.com/upload/vod/2019-01-16/15476134735.jpg","title":"亚瑟3：终极对决","actor":"弗莱迪·海默,米亚·法罗,Robert,Cooper","time":"2019-01-24","link":"http://www.123123mv.com/index.php/voddetail-7117.html","episodes":[{"text":"바로재생","src":"//123123mv.com/dp/mp4.php?url=https://cdn-3.haku99.com/hls/2019/01/16/qLiRaC2O/playlist.m3u8"}],"country":"法国","year":""},{"id":"57ebbc0a3a53912915dc51483479c672","type":"movie","week":"m","img":"http://www.666zy.com/upload/vod/2019-01-19/15479003780.jpg","title":"超级霸王2","actor":"Pete","time":"2019-01-24","link":"http://www.123123mv.com/index.php/voddetail-7473.html","episodes":[{"text":"바로재생","src":"//123123mv.com/dp/mp4.php?url=https://cdn-3.haku99.com/hls/2019/01/19/AliKT63L/playlist.m3u8"}],"country":"美国","year":""},{"id":"08d4d94c4bf87a2e4cbe63b6c4a652eb","type":"movie","week":"m","img":"http://www.666zy.com/upload/vod/2019-01-16/15476242203.jpg","title":"最小的天使","actor":"弗莱迪·海默,米亚·法罗,Robert,Cooper","time":"2019-01-24","link":"http://www.123123mv.com/index.php/voddetail-7124.html","episodes":[{"text":"바로재생","src":"//123123mv.com/dp/mp4.php?url=https://cdn-3.haku99.com/hls/2019/01/16/FZ3uKdEU/playlist.m3u8"}],"country":"美国","year":""},{"id":"af941e88304fc323d2637cf9a66b409b","type":"movie","week":"m","img":"http://www.666zy.com/upload/vod/2019-01-19/15479003702.jpg","title":"弄假成真","actor":"John","time":"2019-01-24","link":"http://www.123123mv.com/index.php/voddetail-7478.html","episodes":[{"text":"바로재생","src":"//123123mv.com/dp/mp4.php?url=https://cdn-3.haku99.com/hls/2019/01/19/Q8OaTZGG/playlist.m3u8"}],"country":"美国","year":""},{"id":"f568e3f312acda33fce9c5ea79b67368","type":"movie","week":"m","img":"http://www.666zy.com/upload/vod/2019-01-16/154761349918.jpg","title":"人工智能","actor":"海利·乔·奥斯蒙,弗兰西丝·奥康纳,山姆·洛巴兹,杰克·托马斯,裘德·洛,威廉·赫特,肯·梁,克拉克·格雷格,凯文·苏斯曼,汤姆·加洛普,Eugene,艾普尔·格雷斯,马特·温斯顿,萨布丽娜·格德维奇,Theo","time":"2019-01-24","link":"http://www.123123mv.com/index.php/voddetail-7123.html","episodes":[{"text":"바로재생","src":"//123123mv.com/dp/mp4.php?url=https://cdn-3.haku99.com/hls/2019/01/16/1Lxu2qUJ/playlist.m3u8"}],"country":"美国","year":""},{"id":"e2688b65ef4a4daffd10275f9d9efe88","type":"movie","week":"m","img":"http://www.666zy.com/upload/vod/2019-01-08/15468857346.jpg","title":"星际之门：时空连续","actor":"Ben,Michael,Amanda,Christopher,Beau","time":"2019-01-24","link":"http://www.123123mv.com/index.php/voddetail-7481.html","episodes":[{"text":"BD720P中字","src":"//123123mv.com/dp/mp4.php?url=https://cdn-3.haku99.com/hls/2019/01/19/0yumatJ0/playlist.m3u8"}],"country":"加拿大","year":""},{"id":"39a40b5b548675a39993481d6ff4be42","type":"movie","week":"m","img":"http://www.666zy.com/upload/vod/2019-01-16/154761350815.jpg","title":"生死狙击","actor":"马克·沃尔伯格,凯特·玛拉,迈克尔·佩纳,丹尼·格洛弗,伊莱亚斯·科泰斯,罗娜·迈特拉","time":"2019-01-24","link":"http://www.123123mv.com/index.php/voddetail-7127.html","episodes":[{"text":"바로재생","src":"//123123mv.com/dp/mp4.php?url=https://cdn-3.haku99.com/hls/2019/01/16/WR6xoWdc/playlist.m3u8"}],"country":"美国","year":""},{"id":"f3e4de21a62cae8427367fa2166bd0d2","type":"movie","week":"m","img":"http://www.666zy.com/upload/vod/2019-01-19/154790037419.jpg","title":"冒牌教练","actor":"康斯坦丁·哈宾斯基,Ivan,米拉·乔沃维奇","time":"2019-01-24","link":"http://www.123123mv.com/index.php/voddetail-7479.html","episodes":[{"text":"BD中英双字幕","src":"//123123mv.com/dp/mp4.php?url=https://cdn-3.haku99.com/hls/2019/01/19/uzE7i312/playlist.m3u8"}],"country":"俄罗斯","year":""},{"id":"493015216204c764f42a824902c3c35d","type":"movie","week":"m","img":"http://www.666zy.com/upload/vod/2019-01-16/15476242202.jpg","title":"邪恶新世界","actor":"George,Freddie,Sigourney,Andy,Sarah","time":"2019-01-24","link":"http://www.123123mv.com/index.php/voddetail-7126.html","episodes":[{"text":"바로재생","src":"//123123mv.com/dp/mp4.php?url=https://cdn-3.haku99.com/hls/2019/01/16/ZLxL7i62/playlist.m3u8"}],"country":"美国","year":""},{"id":"3ab4ffa439e90f310d3d5470a6289ba0","type":"movie","week":"m","img":"http://www.666zy.com/upload/vod/2019-01-19/201901191547884044.png","title":"正义的抉择","actor":"","time":"2019-01-24","link":"http://www.123123mv.com/index.php/voddetail-7482.html","episodes":[{"text":"바로재생","src":"//123123mv.com/dp/mp4.php?url=https://cdn-3.haku99.com/hls/2019/01/19/a0wXDgDu/playlist.m3u8"}],"country":"美国","year":""},{"id":"16e056df4a8bebfc0a9d93a0753a75a8","type":"movie","week":"m","img":"http://www.666zy.com/upload/vod/2019-01-16/15476242290.jpg","title":"誓不遗忘","actor":"Paz,Simon,Ken","time":"2019-01-24","link":"http://www.123123mv.com/index.php/voddetail-7130.html","episodes":[{"text":"바로재생","src":"//123123mv.com/dp/mp4.php?url=https://cdn-3.haku99.com/hls/2019/01/15/pfaPA4lh/playlist.m3u8"}],"country":"美国","year":""},{"id":"42d14433161b6de7c5878d907c555abf","type":"movie","week":"m","img":"http://www.666zy.com/upload/vod/2019-01-19/15479003792.jpg","title":"我去世的吃醋女友","actor":"Eva,Paul,Lake,Jason,Lindsay","time":"2019-01-24","link":"http://www.123123mv.com/index.php/voddetail-7487.html","episodes":[{"text":"BD中字1280终极收藏版","src":"//123123mv.com/dp/mp4.php?url=https://cdn-3.haku99.com/hls/2019/01/19/j2BSRALW/playlist.m3u8"}],"country":"美国","year":""},{"id":"528c2c8c349cb16c270e5ab1d3d06f35","type":"movie","week":"m","img":"http://www.666zy.com/upload/vod/2019-01-16/154761350816.jpg","title":"黑暗之中","actor":"娜塔莉·多默尔,艾德·斯克林,艾米丽·拉塔科斯基,乔莉·理查德森,尼尔·马斯克尔,詹姆斯·卡沙莫,扬·贝弗特,丹尼尔·厄根,奥莱加·费多罗,莱克茜·本博-哈特,迈克尔·博特,Bern,Amber,Kim,Stefan","time":"2019-01-24","link":"http://www.123123mv.com/index.php/voddetail-7129.html","episodes":[{"text":"바로재생","src":"//123123mv.com/dp/mp4.php?url=https://cdn-3.haku99.com/hls/2019/01/16/G8o2tNQq/playlist.m3u8"}],"country":"美国","year":""},{"id":"e5ee6a40bc484bbb80ebfd53f318e5ff","type":"movie","week":"m","img":"http://www.666zy.com/upload/vod/2019-01-20/15479263840.jpg","title":"希瑞&希曼圣诞特别篇","actor":"John,Alan,Linda,Lana,Melendy","time":"2019-01-24","link":"http://www.123123mv.com/index.php/voddetail-7491.html","episodes":[{"text":"바로재생","src":"//123123mv.com/dp/mp4.php?url=https://cdn-3.haku99.com/hls/2019/01/19/5ycYkhSl/playlist.m3u8"}],"country":"美国","year":""},{"id":"ccc8e36fb722c65761b96613e0f60002","type":"movie","week":"m","img":"http://www.666zy.com/upload/vod/2019-01-16/154761350918.jpg","title":"神秘代码","actor":"Nicolas,Chandler,Rose,Lara,D.G.","time":"2019-01-24","link":"http://www.123123mv.com/index.php/voddetail-7131.html","episodes":[{"text":"바로재생","src":"//123123mv.com/dp/mp4.php?url=https://cdn-3.haku99.com/hls/2019/01/16/4kzYYrjh/playlist.m3u8"}],"country":"美国","year":""},{"id":"3f27008845c2b4dd7c55d4b19a8164b1","type":"movie","week":"m","img":"http://www.666zy.com/upload/vod/2019-01-20/15479535446.jpg","title":"时间中的孩子","actor":"本尼迪克特·康伯巴奇,凯莉·麦克唐纳,斯蒂芬·坎贝尔·莫尔,莎卡亚·瑞丝,安娜·玛德蕾,约翰·霍普金斯,露西·莱曼,理查德·杜登,杰拉尔丁·亚力山大,艾略特·利维,凯伦·布莱森,埃勒维兹·亨伍德,劳伦斯·斯佩尔曼,杰拉德·摩纳科","time":"2019-01-24","link":"http://www.123123mv.com/index.php/voddetail-7496.html","episodes":[{"text":"HD","src":"//123123mv.com/dp/mp4.php?url=https://cdn-3.haku99.com/hls/2019/01/20/kYVMEN2g/playlist.m3u8"}],"country":"英国","year":""},{"id":"e80187536e7b25485b60ae7a203c60a4","type":"movie","week":"m","img":"http://www.666zy.com/upload/vod/2019-01-16/154762422312.jpg","title":"罗斯福：美国混蛋","actor":"巴瑞·波斯威克,Lin,布鲁斯·麦克吉尔","time":"2019-01-24","link":"http://www.123123mv.com/index.php/voddetail-7137.html","episodes":[{"text":"바로재생","src":"//123123mv.com/dp/mp4.php?url=https://cdn-3.haku99.com/hls/2019/01/16/HDSXldpC/playlist.m3u8"}],"country":"美国","year":""}]