[{"id":"ebefe403c98e987c4f43c8ca6636b8ed","type":"movie","week":"m","img":"http://www.666zy.com/upload/vod/2019-01-12/154726875815.jpg","title":"致命一击","actor":"山姆·洛克威尔,威廉姆·H·梅西,梅丽莎·里奥,杰弗里·怀特,詹森·艾萨克,凯利·蕾莉,泰德·拉文,奥菲利亚·拉维邦德,艾米·斯洛安","time":"2019-01-24","link":"http://www.123123mv.com/index.php/voddetail-6286.html","episodes":[{"text":"바로재생","src":"//123123mv.com/dp/mp4.php?url=https://cdn-3.haku99.com/hls/2019/01/10/Q7t7ZcMj/playlist.m3u8"}],"country":"美国","year":""},{"id":"9fbddb4264a0ab440dd04f39209f6ac5","type":"movie","week":"m","img":"http://www.666zy.com/upload/vod/2019-01-21/154802960316.jpg","title":"我不在那儿","actor":"凯特·布兰切特,本·卫肖,克里斯蒂安·贝尔,理查·基尔,希斯·莱杰,朱丽安·摩尔,皮特·弗雷德曼,金·戈顿,夏洛特·甘斯布,米歇尔·威廉姆斯","time":"2019-01-24","link":"http://www.123123mv.com/index.php/voddetail-7526.html","episodes":[{"text":"바로재생","src":"//123123mv.com/dp/mp4.php?url=https://cdn-3.haku99.com/hls/2019/01/20/lCWHLZ10/playlist.m3u8"}],"country":"美国","year":""},{"id":"704fc7b255a1b1d8d82c5c93a7447f69","type":"movie","week":"m","img":"http://www.666zy.com/upload/vod/2019-01-12/15472946261.jpg","title":"黑暗真相","actor":"金·寇兹,凯文·杜兰,福里斯特·惠特克,安迪·加西亚","time":"2019-01-24","link":"http://www.123123mv.com/index.php/voddetail-6289.html","episodes":[{"text":"바로재생","src":"//123123mv.com/dp/mp4.php?url=https://cdn-3.haku99.com/hls/2019/01/10/uUZzV15Y/playlist.m3u8"}],"country":"加拿大","year":""},{"id":"f276d52cf6c352b4ff9e79261549dad7","type":"movie","week":"m","img":"http://www.666zy.com/upload/vod/2019-01-21/15480298530.jpg","title":"潇洒有情天","actor":"Whoopi,Mary-Louise,Drew,马修·麦康纳","time":"2019-01-24","link":"http://www.123123mv.com/index.php/voddetail-7530.html","episodes":[{"text":"바로재생","src":"//123123mv.com/dp/mp4.php?url=https://cdn-3.haku99.com/hls/2019/01/20/5SPACApD/playlist.m3u8"}],"country":"美国","year":""},{"id":"f81d8e82340ea4787db2b17ba15e42dd","type":"movie","week":"m","img":"http://www.666zy.com/upload/vod/2019-01-12/15472687440.jpg","title":"观光客","actor":"爱丽丝·洛维,史蒂夫·奥拉姆,Eileen,莫妮卡·杜兰,乔纳森·阿里斯,Richard,Richard,托尼·威","time":"2019-01-24","link":"http://www.123123mv.com/index.php/voddetail-6290.html","episodes":[{"text":"바로재생","src":"//123123mv.com/dp/mp4.php?url=https://cdn-3.haku99.com/hls/2019/01/10/nUz5yqll/playlist.m3u8"}],"country":"英国","year":""},{"id":"1bbce103e6e50b28f66d193b2c79a8c3","type":"movie","week":"m","img":"http://www.666zy.com/upload/vod/2019-01-21/154802961016.jpg","title":"野僵尸","actor":"Joe,梅格·西奥妮,Matthew,Amelia","time":"2019-01-24","link":"http://www.123123mv.com/index.php/voddetail-7538.html","episodes":[{"text":"高清1280版中字","src":"//123123mv.com/dp/mp4.php?url=https://cdn-3.haku99.com/hls/2019/01/20/a5mOnSq9/playlist.m3u8"}],"country":"美国","year":""},{"id":"88cfa12515cddf5ffd44741c287b5a20","type":"movie","week":"m","img":"http://www.666zy.com/upload/vod/2019-01-12/15472946262.jpg","title":"诸神之锤","actor":"查理·比尤利,克莱夫·斯坦登,詹姆斯·卡沙莫,艾略特·科万,格娜萨斯·巴伯,迈克尔·吉普森,Guy,Theo,Alexandra,芬莱·罗伯特森,Michael","time":"2019-01-24","link":"http://www.123123mv.com/index.php/voddetail-6291.html","episodes":[{"text":"바로재생","src":"//123123mv.com/dp/mp4.php?url=https://cdn-3.haku99.com/hls/2019/01/10/NUucaQEv/playlist.m3u8"}],"country":"英国","year":""},{"id":"f5722bc511fc96a72279ff7aa586f960","type":"movie","week":"m","img":"http://www.666zy.com/upload/vod/2019-01-21/154802984715.jpg","title":"宿主","actor":"西尔莎·罗南,马克斯·艾龙斯,杰克·阿贝尔,波伊德·霍布鲁克,威廉·赫特,黛安·克鲁格,弗兰西丝·费舍,钱德勒·坎特布瑞,博基姆·伍德拜因","time":"2019-01-24","link":"http://www.123123mv.com/index.php/voddetail-7537.html","episodes":[{"text":"바로재생","src":"//123123mv.com/dp/mp4.php?url=https://cdn-3.haku99.com/hls/2019/01/16/X37mSspN/playlist.m3u8"}],"country":"美国","year":""},{"id":"6c04ad75569d3d23ec32aed4f586f588","type":"movie","week":"m","img":"http://www.666zy.com/upload/vod/2019-01-12/15472946263.jpg","title":"虎胆龙威2","actor":"布鲁斯·威利斯,邦妮·比蒂丽娅,威廉·阿瑟东,Reginald,弗兰科·尼罗","time":"2019-01-24","link":"http://www.123123mv.com/index.php/voddetail-6293.html","episodes":[{"text":"바로재생","src":"//123123mv.com/dp/mp4.php?url=https://cdn-3.haku99.com/hls/2019/01/10/MMPo7YoC/playlist.m3u8"}],"country":"美国","year":""},{"id":"1c05fc29eeebd49976cd927cc1f32e6d","type":"movie","week":"m","img":"http://www.666zy.com/upload/vod/2018-11-08/154168671413.jpg","title":"华尔街之狼","actor":"莱昂纳多·迪卡普里奥,乔纳·希尔,玛格特·罗比,马修·麦康纳,凯尔·钱德勒,罗伯·莱纳,乔·博恩瑟,让·杜雅尔丹,克里斯汀,卡塔莉娜·凯斯","time":"2019-01-24","link":"http://www.123123mv.com/index.php/voddetail-7539.html","episodes":[{"text":"바로재생","src":"//123123mv.com/dp/mp4.php?url=https://cdn-2.haku99.com/hls/2018/12/27/G58VH87Z/playlist.m3u8"},{"text":"无删减","src":"//123123mv.com/dp/mp4.php?url=https://cdn-3.haku99.com/hls/2019/01/20/5IXppnxK/playlist.m3u8"}],"country":"美国","year":""},{"id":"aaa0864867a3971ea958408a36a7fbef","type":"movie","week":"m","img":"http://www.666zy.com/upload/vod/2019-01-12/15472946264.jpg","title":"虎胆龙威3","actor":"布鲁斯·威利斯,杰瑞米·艾恩斯,塞缪尔·杰克逊,1056126,考林·加普","time":"2019-01-24","link":"http://www.123123mv.com/index.php/voddetail-6295.html","episodes":[{"text":"바로재생","src":"//123123mv.com/dp/mp4.php?url=https://cdn-3.haku99.com/hls/2019/01/10/WKhZpz7p/playlist.m3u8"}],"country":"美国","year":""},{"id":"21ec41f6caab3f38d41617da126a10c2","type":"movie","week":"m","img":"http://www.666zy.com/upload/vod/2019-01-21/15480298532.jpg","title":"母亲节","actor":"安娜·麦克西维尔·马丁,薇琪·麦克卢尔,丹尼尔·梅斯,大卫·威尔莫特,西蒙妮·柯比,Annabelle,Wendy,Trevor","time":"2019-01-24","link":"http://www.123123mv.com/index.php/voddetail-7548.html","episodes":[{"text":"BD中英双字","src":"//123123mv.com/dp/mp4.php?url=https://cdn-3.haku99.com/hls/2019/01/20/zN6Kv9Wk/playlist.m3u8"}],"country":"英国","year":""},{"id":"0cda345bf8ebb4bffcb736736ff37ff0","type":"movie","week":"m","img":"http://www.666zy.com/upload/vod/2019-01-12/154729462710.jpg","title":"惊声尖叫3","actor":"Neve,Liev,Courteney,David,Jamie","time":"2019-01-24","link":"http://www.123123mv.com/index.php/voddetail-6298.html","episodes":[{"text":"바로재생","src":"//123123mv.com/dp/mp4.php?url=https://cdn-3.haku99.com/hls/2019/01/10/obWy3BKc/playlist.m3u8"}],"country":"美国","year":""},{"id":"3cf62419b8e4d1ed866cadcaba6f2754","type":"movie","week":"m","img":"http://www.666zy.com/upload/vod/2019-01-21/154806868111.jpg","title":"憨憨公主的心思","actor":"卡米尔·科坦,塞西尔·博兰德,露·卡顿,Antony,罗西·马洪·德·莫纳汉,玛丽·克里斯汀·亚当,Stéphane,凯德·麦拉德","time":"2019-01-24","link":"http://www.123123mv.com/index.php/voddetail-7547.html","episodes":[{"text":"바로재생","src":"//123123mv.com/dp/mp4.php?url=https://cdn-3.haku99.com/hls/2019/01/21/rmmruzPT/playlist.m3u8"}],"country":"法国","year":""},{"id":"1265c25eb3b6a986d7dd27b72a20ce67","type":"movie","week":"m","img":"http://www.666zy.com/upload/vod/2019-01-12/154729463813.jpg","title":"神偷艳贼","actor":"卡梅隆·迪亚茨,柯林·菲尔斯,艾伦·瑞克曼,史坦利·图齐,克劳斯·利特曼,汤姆·康特奈","time":"2019-01-24","link":"http://www.123123mv.com/index.php/voddetail-6301.html","episodes":[{"text":"바로재생","src":"//123123mv.com/dp/mp4.php?url=https://cdn-3.haku99.com/hls/2019/01/10/GtW4H8kN/playlist.m3u8"}],"country":"美国","year":""},{"id":"7dfad0f25f992091af87f0d89d546617","type":"movie","week":"m","img":"http://www.666zy.com/upload/vod/2019-01-21/15480298534.jpg","title":"一切过后","actor":"麦卡·梦露,杰瑞米·艾伦·怀特,玛丽莎·托梅,吉娜·格申,迪恩·文特斯,萨莎·莱恩,乔·基瑞,森德希·拉玛莫西,奥莉维亚·卢卡尔迪,凯莉·索恩,莱亚·吉斯特德,比尔·萨奇,彼得·瓦克,Marlyne,埃里克·詹森,克里斯蒂娜·谢勒,伊维特麦奎因费伊,Karl,Eric,Adrianne,罗丝玛丽·霍华德","time":"2019-01-24","link":"http://www.123123mv.com/index.php/voddetail-7554.html","episodes":[{"text":"1080p中字","src":"//123123mv.com/dp/mp4.php?url=https://cdn-3.haku99.com/hls/2019/01/20/9G3nYbba/playlist.m3u8"}],"country":"美国","year":""},{"id":"6f593ba506f3bfa067725b6056b20604","type":"movie","week":"m","img":"http://www.666zy.com/upload/vod/2019-01-12/154729463814.jpg","title":"冰雪勇士2：空降信条","actor":"Corbin,David,Jasen","time":"2019-01-24","link":"http://www.123123mv.com/index.php/voddetail-6304.html","episodes":[{"text":"바로재생","src":"//123123mv.com/dp/mp4.php?url=https://cdn-3.haku99.com/hls/2019/01/10/n1cEzPjJ/playlist.m3u8"}],"country":"美国","year":""},{"id":"2c5f882563625cf6498aeb77e734704d","type":"movie","week":"m","img":"http://www.666zy.com/upload/vod/2019-01-21/154806868318.jpg","title":"贼王","actor":"迈克尔·凯恩,迈克尔·刚本,查理·考克斯,雷·温斯顿,吉姆·布劳德本特,汤姆·康特奈,弗兰西丝卡·安妮丝","time":"2019-01-24","link":"http://www.123123mv.com/index.php/voddetail-7553.html","episodes":[{"text":"바로재생","src":"//123123mv.com/dp/mp4.php?url=https://cdn-3.haku99.com/hls/2019/01/21/kTGo8MPP/playlist.m3u8"}],"country":"英国","year":""},{"id":"f61c358144a2320b4824cbec647f73da","type":"movie","week":"m","img":"http://www.666zy.com/upload/vod/2019-01-12/15472946354.jpg","title":"怒火救援","actor":"Denzel,Dakota,Radha,Marc,Christopher,Giancarlo,Rachel,Jesús,Mickey","time":"2019-01-24","link":"http://www.123123mv.com/index.php/voddetail-6305.html","episodes":[{"text":"바로재생","src":"//123123mv.com/dp/mp4.php?url=https://cdn-3.haku99.com/hls/2019/01/10/JKIzziFJ/playlist.m3u8"}],"country":"美国","year":""},{"id":"510af764a3e14b4ca026277bec1203d9","type":"movie","week":"m","img":"http://www.666zy.com/upload/vod/2019-01-21/154806869412.jpg","title":"比基尼激情春假","actor":"Rachel,Virginia,Samantha","time":"2019-01-24","link":"http://www.123123mv.com/index.php/voddetail-7552.html","episodes":[{"text":"바로재생","src":"//123123mv.com/dp/mp4.php?url=https://cdn-3.haku99.com/hls/2019/01/21/L55rDh6E/playlist.m3u8"}],"country":"美国","year":""}]